arf/__init__.py
arf/arf.py
arf_mime-1.1.0.dist-info/LICENSE
arf_mime-1.1.0.dist-info/METADATA
arf_mime-1.1.0.dist-info/WHEEL
arf_mime-1.1.0.dist-info/top_level.txt
arf_mime-1.1.0.dist-info/RECORD
