Metadata-Version: 2.1
Name: arf-mime
Version: 1.1.0
Summary: An absctract representation of ARF messages.
Home-page: https://github.com/danielsen/arf
Author: Dan Nielsen
Author-email: dnielsen@fastmail.fm
License: UNKNOWN
Platform: UNKNOWN
Classifier: Programming Language :: Python :: 2
Classifier: Programming Language :: Python :: 3
Classifier: License :: OSI Approved :: GNU General Public License v3 (GPLv3)
Classifier: Operating System :: OS Independent
Requires-Python: >=2.7
